osin/__init__.py
osin/__main__.py
osin/apis/__init__.py
osin/apis/local_osin.py
osin/apis/osin.py
osin/apis/remote_exp.py
osin/apis/remote_osin.py
osin/app.py
osin/config.py
osin/controllers/__init__.py
osin/controllers/exp.py
osin/controllers/report.py
osin/controllers/views.py
osin/formats/__init__.py
osin/formats/hdf5.py
osin/integrations/__init__.py
osin/integrations/ream.py
osin/misc.py
osin/models/__init__.py
osin/models/base.py
osin/models/exp.py
osin/models/exp_data.py
osin/models/migration/__init__.py
osin/models/migration/v_1_6_2_1_7_0.backup
osin/models/report/__init__.py
osin/models/report/auto_table.py
osin/models/report/base_report.py
osin/models/report/dbmodel.py
osin/models/report/index_schema.py
osin/models/report.py.backup
osin/models/views.py
osin/params_helper.py
osin/repository.py
osin/types/__init__.py
osin/types/param_schema.py
osin/types/primitive_type.py
osin/types/pyobject/__init__.py
osin/types/pyobject/base.py
osin/types/pyobject/html.py
osin/types/pyobject_type.py
osin-2.2.3.dist-info/LICENSE
osin-2.2.3.dist-info/METADATA
osin-2.2.3.dist-info/WHEEL
osin-2.2.3.dist-info/RECORD
