Metadata-Version: 2.1
Name: osin
Version: 2.2.3
Summary: Research and Experiments
License: MIT
Author: Binh Vu
Author-email: binh@toan2.com
Requires-Python: >=3.9,<4.0
Classifier: License :: OSI Approved :: MIT License
Classifier: Programming Language :: Python :: 3
Classifier: Programming Language :: Python :: 3.9
Classifier: Programming Language :: Python :: 3.10
Classifier: Programming Language :: Python :: 3.11
Classifier: Programming Language :: Python :: 3.12
Requires-Dist: Flask (>=2.2.2,<3.0.0)
Requires-Dist: gena (>=1.6.6,<2.0.0)
Requires-Dist: h5py (>=3.8.0,<4.0.0)
Requires-Dist: htbuilder (>=0.6.2,<0.7.0)
Requires-Dist: loguru (>=0.7.0,<0.8.0)
Requires-Dist: orjson (>=3.9.0,<4.0.0)
Requires-Dist: peewee (>=3.15.2,<4.0.0)
Requires-Dist: psutil (>=5.9.2,<6.0.0)
Requires-Dist: python-slugify (>=6.1.2,<7.0.0)
Requires-Dist: ream2 (>=3.0.1,<4.0.0)
Requires-Dist: t2-yada (>=1.2.0,<2.0.0)
Requires-Dist: tornado (>=6.2,<7.0)
